sharedlib/__init__.py
sharedlib/config.py
sharedlib/register.py
sharedlib-0.0.1.dist-info/LICENSE
sharedlib-0.0.1.dist-info/METADATA
sharedlib-0.0.1.dist-info/WHEEL
sharedlib-0.0.1.dist-info/top_level.txt
sharedlib-0.0.1.dist-info/RECORD
