Metadata-Version: 2.1
Name: sharedlib
Version: 0.0.1
Summary: Share packages for monorepo services
License: MIT License
Project-URL: Homepage, https://github.com/paqstd-dev/sharedlib
Project-URL: Bug Tracker, https://github.com/paqstd-dev/sharedlib/issues
Keywords: monorepo,shared,sharedlib,lib,repo
Classifier: License :: OSI Approved :: MIT License
Classifier: Programming Language :: Python :: 3
Requires-Python: >=3.8
License-File: LICENSE
